__init__.py
PSVG/Data_Structures.py
PSVG/__init__.py
PSVG/Draw/Base.py
PSVG/Draw/Circle.py
PSVG/Draw/Path.py
PSVG/Draw/Rectangle.py
PSVG/Draw/__init__.py
PSVG/SVG/Base.py
PSVG/SVG/__init__.py
PSVG/Text/Font.py
PSVG/Text/Paragraph.py
PSVG/Text/Table.py
PSVG/Text/Text.py
PSVG/Text/TextBox.py
PSVG/Text/__init__.py
PSVG-0.2.7.dist-info/LICENSE
PSVG-0.2.7.dist-info/METADATA
PSVG-0.2.7.dist-info/WHEEL
PSVG-0.2.7.dist-info/top_level.txt
PSVG-0.2.7.dist-info/RECORD
