Metadata-Version: 2.1
Name: PSVG
Version: 0.2.7
Summary: Python interface for generating SVGs.
Author-email: Carter Bodinger <carterallenbodinger@yahoo.com>
License: GNU GENERAL PUBLIC LICENSE
Project-URL: Homepage, https://github.com/cbodinge/PySVG
Project-URL: Bug Tracker, https://github.com/cbodinge/PySVG/issues
Classifier: Programming Language :: Python :: 3
Classifier: License :: OSI Approved :: GNU General Public License v2 (GPLv2)
Classifier: Operating System :: OS Independent
Requires-Python: >=3.7
License-File: LICENSE
